{
  "project_info": {
    "project_number": "785682309454",
    "firebase_url": "https://jesse-50f7c.firebaseio.com",
    "project_id": "jesse-50f7c",
    "storage_bucket": "jesse-50f7c.appspot.com"
  },
  "client": [
    {
      "client_info": {
        "mobilesdk_app_id": "1:785682309454:android:644334b79eb3b9f2663e1f",
        "android_client_info": {
          "package_name": "com.example.j3enterprise"
        }
      },
      "oauth_client": [
        {
          "client_id": "785682309454-jvcji1rkaar153o1a6ol589grcos7fup.apps.googleusercontent.com",
          "client_type": 3
        }
      ],
      "api_key": [
        {
          "current_key": "AIzaSyBQSf3h9-RZC6cIeMYiYBYMA71mtsZDO5M"
        }
      ],
      "services": {
        "appinvite_service": {
          "other_platform_oauth_client": [
            {
              "client_id": "785682309454-jvcji1rkaar153o1a6ol589grcos7fup.apps.googleusercontent.com",
              "client_type": 3
            }
          ]
        }
      }
    }
  ],
  "configuration_version": "1"
}